{"2024-01-23":{"count":260,"repetition":335,"Python":54,"Javascript":25,"C++":144,"Java":115,"Go":0,"Kotlin":0},"2023-11-26":{"count":224,"repetition":271,"Python":36,"Javascript":25,"C++":137,"Java":76,"Go":0,"Kotlin":0},"1995-01-01":{"count":0,"repetition":0,"Python":0,"Javascript":0,"C++":0,"Java":0,"Go":0,"Kotlin":0},"2024-02-10":{"count":274,"repetition":375,"Python":62,"Javascript":33,"C++":145,"Java":123,"Go":7,"Kotlin":7},"2024-02-17":{"count":301,"repetition":410,"Python":75,"Javascript":38,"C++":148,"Java":129,"Go":12,"Kotlin":11},"2024-02-23":{"count":315,"repetition":430,"Python":83,"Javascript":39,"C++":148,"Java":135,"Go":14,"Kotlin":13},"2024-03-02":{"count":330,"repetition":453,"Python":90,"Javascript":41,"C++":150,"Java":140,"Go":16,"Kotlin":16},"2024-03-10":{"count":344,"repetition":475,"Python":97,"Javascript":43,"C++":153,"Java":144,"Go":19,"Kotlin":19},"2024-03-15":{"count":351,"repetition":488,"Python":101,"Javascript":45,"C++":156,"Java":147,"Go":22,"Kotlin":21}}