{
    "id": "a073f9df-54ec-41df-91ab-7787766bff0c",
    "title": "[독서] SQL 자격 실전 문제 완독",
    "Status": "Done",
    "분류": "독서",
    "Tag": ["Oracle", "DBMS"],
    "기간": {"start": "2024-02-26T00:00:00.000+00:00", "end": "2024-03-06T00:00:00.000+00:00"},
    "완료율": "100%",
    "세부계획": [
        {"id": "edac74e0-74d8-4641-b79c-41f2d186acfe", "세부계획": "[SQL] 4. SQL 전문가 실기문제 (6문제)", "Date": {"start": "2024-02-26", "end": "2024-03-02"}, "진행상태": "Done", "Done": true},
        {"id": "feefaa5d-7580-4a77-92e0-f81daddd7ed6", "세부계획": "[SQL] 3-2. SQL 분석 도구 (11문제)", "Date": {"start": "2024-02-27", "end": null}, "진행상태": "Done", "Done": true},
        {"id": "7eb9177f-5030-48a5-b805-07113e420bc9", "세부계획": "[SQL] 3-1. SQL 수행 구조 (19문제)", "Date": {"start": "2024-02-27", "end": null}, "진행상태": "Done", "Done": true},
        {"id": "c8178556-909d-4f52-8ee8-c8d3a0d2bf7e", "세부계획": "[SQL] 3-4. 조인 튜닝 (24문제)", "Date": {"start": "2024-02-28", "end": "2024-02-29"}, "진행상태": "Done", "Done": true},
        {"id": "33652d58-4abb-47c3-829e-341ab2506caa", "세부계획": "[SQL] 3-3. 인덱스 튜닝 (23문제)", "Date": {"start": "2024-02-28", "end": null}, "진행상태": "Done", "Done": true},
        {"id": "b50a228c-93cf-4729-8c74-fe57c0113ba7", "세부계획": "[SQL] 3-6. 고급 SQL 튜닝 (24문제)", "Date": {"start": "2024-02-29", "end": null}, "진행상태": "Done", "Done": true},
        {"id": "32d3dfab-cd7e-4e11-a2a0-9863ab757477", "세부계획": "[SQL] 3-5. SQL 옵티마이저 (17문제)", "Date": {"start": "2024-02-29", "end": null}, "진행상태": "Done", "Done": true},
        {"id": "696bf55a-a7b5-4e47-bc6a-83aee12039d9", "세부계획": "[SQL] 1-2. 데이터 모델과 SQL (17문제)", "Date": {"start": "2024-03-03", "end": null}, "진행상태": "Done", "Done": true},
        {"id": "2856cdc9-9eef-4993-b38a-dba13f5dfe51", "세부계획": "[SQL] 1-1. 데이터 모델링의 이해 (33문제)", "Date": {"start": "2024-03-03", "end": null}, "진행상태": "Done", "Done": true},
        {"id": "2218ecfe-8fb1-4265-bcee-b16309d680cb", "세부계획": "[SQL] 2-1. SQL 기본 (50문제)", "Date": {"start": "2024-03-04", "end": null}, "진행상태": "Done", "Done": true},
        {"id": "26a4929b-cedf-4dac-8e2f-1902b259b147", "세부계획": "[SQL] 2-2. SQL 활용 (50문제)", "Date": {"start": "2024-03-05", "end": null}, "진행상태": "Done", "Done": true},
        {"id": "fc3464a9-a44d-41a9-9729-b7a66ba65adc", "세부계획": "[SQL] 2-3. 관리 구문 (26문제)", "Date": {"start": "2024-03-06", "end": null}, "진행상태": "Done", "Done": true}
    ]
}
