{"object":"page","id":"99b5cdfe-8675-48c4-9e1b-573f9627085b","created_time":"2022-12-15T04:20:00.000Z","last_edited_time":"2023-03-12T08:12:00.000Z","created_by":{"object":"user","id":"d7eb6fe5-743d-40ab-98c0-5adf6ae2d956"},"last_edited_by":{"object":"user","id":"d7eb6fe5-743d-40ab-98c0-5adf6ae2d956"},"cover":null,"icon":null,"parent":{"type":"database_id","database_id":"12429ec5-9cb1-4e1b-a82b-3d77cedc7e9c"},"archived":false,"properties":{"Date":{"id":"%3CUkF","type":"date","date":null},"남은 시간":{"id":"KAG%40","type":"rollup","rollup":{"type":"array","array":[],"function":"show_original"}},"단위계획 수":{"id":"QkTM","type":"formula","formula":{"type":"number","number":null}},"생각나는 목표들":{"id":"VMvI","type":"relation","relation":[],"has_more":false},"Tag":{"id":"VPPQ","type":"multi_select","multi_select":[{"id":"cda6c33a-7f61-4d35-ab2e-3feeec5a4134","name":"Node.js","color":"pink"},{"id":"aa458f79-3ec5-4eb8-8bee-9b805bef9952","name":"Javascript","color":"orange"}]},"장기/단기":{"id":"XBwf","type":"multi_select","multi_select":[{"id":"3f69333d-82ad-4ccf-9f9b-77cc60085c0e","name":"단기","color":"blue"}]},"단위계획":{"id":"%5EeHn","type":"rollup","rollup":{"type":"array","array":[],"function":"show_unique"}},"관련일정":{"id":"p%3Cme","type":"relation","relation":[],"has_more":false},"완료":{"id":"pJum","type":"checkbox","checkbox":true},"Column":{"id":"q%3Czy","type":"rollup","rollup":{"type":"array","array":[],"function":"show_original"}},"완료율":{"id":"~Wpc","type":"rollup","rollup":{"type":"array","array":[],"function":"show_original"}},"Name":{"id":"title","type":"title","title":[{"type":"text","text":{"content":"[공부] Node.js","link":null},"annotations":{"bold":false,"italic":false,"strikethrough":false,"underline":false,"code":false,"color":"default"},"plain_text":"[공부] Node.js","href":null}]}},"url":"https://www.notion.so/Node-js-99b5cdfe867548c49e1b573f9627085b"}