{"id":"f974fd37-7d00-4cbb-9213-60e8b1ac99bd","title":"[공모전] KB증권 스마트워치 어플 만들기 ","Status":"Done","분류":"프로젝트","Tag":["Kotlin","Java","Android"],"기간":{"start":"2022-02-09T00:00:00.000+00:00","end":"2022-03-10T00:00:00.000+00:00"},"완료율":"91%","세부계획":[{"id":"c33b54b2-b52d-49e9-8951-191d201e5d4b","세부계획":" 개발환경 구축","Date":{"start":"2022-02-09","end":"2022-02-20"},"진행상태":"In Progress","Done":false},{"id":"7c8333b0-3d89-42b2-bdbe-7981038498de","세부계획":"안드로이드 스튜디오 첫 어플리케이션 ","Date":{"start":"2022-02-11","end":null},"진행상태":"Done","Done":true},{"id":"1ea4296b-b06f-454b-8897-6559b1b20399","세부계획":"안드로이드 스튜디오 : 앱 메니페스토","Date":{"start":"2022-02-12","end":"2022-02-19"},"진행상태":"Done","Done":true},{"id":"4406d945-660c-4c92-9fd6-4fb613c8ed62","세부계획":"안드로이스 스튜디오 : 레이아웃 에디터 및 반응형 UI","Date":{"start":"2022-02-12","end":"2022-03-05"},"진행상태":"TODO","Done":true},{"id":"12658030-5c7f-4230-a10c-ad9449f39f80","세부계획":"안드로이드 개발 공부  : gradle 및 빌드 구성","Date":{"start":"2022-02-12","end":"2022-02-20"},"진행상태":"Done","Done":true},{"id":"71c451b6-336a-4d2c-8298-1a979b11877e","세부계획":"안드로이드 개발공부 : 코틀린","Date":{"start":"2022-02-13","end":"2022-02-17"},"진행상태":"Done","Done":true},{"id":"37b27b7a-061a-4c73-90c2-bf0ffe35b07d","세부계획":"wear OS 첫 어플리케이션 빌드 및 디버깅","Date":{"start":"2022-02-20","end":"2022-03-05"},"진행상태":"Done","Done":true},{"id":"6c3c7daf-b855-44d2-bbc3-596c91d758f5","세부계획":"wear OS 첫 어플리케이션 에뮬레이터 동작","Date":{"start":"2022-02-20","end":"2022-03-05"},"진행상태":"Done","Done":true},{"id":"04c03790-fbf4-4468-869d-8973878fc9ae","세부계획":"안드로이드 스튜디오 ","Date":{"start":"2022-02-20","end":"2022-03-05"},"진행상태":"Done","Done":true},{"id":"07bd2f7a-7ec5-4f34-9517-ca380b36aaba","세부계획":"기한 1","Date":{"start":"2022-02-21","end":null},"진행상태":"TODO","Done":true},{"id":"d0e7c1b6-97fc-48db-97fb-2e5f0bd5a10f","세부계획":"기한 2","Date":{"start":"2022-03-10","end":null},"진행상태":"TODO","Done":true}]}