{"id":"2186fa5b-99c1-44eb-bcad-25a9a842693c","_요일태그":{"id":"%3AA%3Bv","type":"checkbox","checkbox":false},"스케쥴 Done":{"id":"%3BjvB","type":"rollup","rollup":{"type":"array","array":[{"type":"checkbox","checkbox":false}],"function":"show_original"}},"_on_this_weak":{"id":"DKC%7C","type":"formula","formula":{"type":"boolean","boolean":true}},"우선순위":{"id":"FHMW","type":"select","select":null},"_시간":{"id":"IM%3CT","type":"select","select":null},"_이번주":{"id":"MfDV","type":"formula","formula":{"type":"boolean","boolean":false}},"_yesterday":{"id":"QWj_","type":"formula","formula":{"type":"boolean","boolean":false}},"_today":{"id":"R%40%3Dv","type":"formula","formula":{"type":"boolean","boolean":false}},"_on_next_weak":{"id":"TFRN","type":"formula","formula":{"type":"boolean","boolean":true}},"Date":null,"_요일":{"id":"gI%40z","type":"formula","formula":{"type":"string","string":null}},"Done":false,"_주중목표":{"id":"itTI","type":"checkbox","checkbox":false},"_hours":{"id":"owmp","type":"date","date":null},"진행상태":"TODO","스케쥴 시간":{"id":"~Y%5Dz","type":"rollup","rollup":{"type":"array","array":[{"type":"date","date":null}],"function":"show_original"}},"관련 스케쥴":{"id":"~ub%60","type":"relation","relation":[{"id":"8d8128a6-3554-408a-943a-f2e9cf36c9ce"}],"has_more":false},"세부계획":"[도커/쿠버네티스] 11. 애플리케이션 배포를 위한 고급 설정"}